pygeoapi_mssql_provider/__init__.py
pygeoapi_mssql_provider/mssql.py
pygeoapi_mssql_provider-0.2.1.dist-info/WHEEL
pygeoapi_mssql_provider-0.2.1.dist-info/METADATA
pygeoapi_mssql_provider-0.2.1.dist-info/RECORD
